[
    {
        "type": "title",
        "content": "sext"
    },
    {
        "type": "title",
        "content": "ശനി മദ്ധ്യാഹ്നം"
    },
    {
        "type": "link-collapsible",
        "file": "commonprayers/kauma.json"
    },
    {
        "type": "heading",
        "content": "കോലൊ"
    },
    {
        "type": "subheading",
        "content": "(പതഹ്ലീത എദഹനോനോക്ക്)"
    },
    {
        "type": "song",
        "content": "കന്യകമറിയമിനെക്കണ്ടു\nനൂതനവാനിടമായ് വിശ്വം\nലോകങ്ങൾക്കും മുമ്പായ് പേ-\nരുള്ളൊരു നീതിമഹാസൂര്യൻ\n/tമറിയാമ്മീന്നുദയം ചെയ്തു\n/tവഞ്ചനയാമിരുൾ മായിച്ചു\nധന്യൻ തൽ സ്മരണ-\nയ്ക്കുന്നതിയേറ്റം കൽപ്പിച്ചോൻ,"
    },
    {
        "type": "subtext",
        "content": "ബാറെക്മോർ. ശൂബഹൊ...."
    },
    {
        "type": "song",
        "content": "വിശ്വാസത്തിൻ ശിൽപ്പികളാം\nനിബിയൻമാർക്കായി ശ്ലോമോ\nസഭതൻ കെട്ടുപണിക്കാരാം\nശ്ലീഹന്മാർക്കായി ശ്ലോമോ\n/tശ്ലോമോ തൻ നാഥൻ തന്നെ\n/t സ്നേഹിച്ചോരാം സഹദേർക്കും\nഅവരെ മാനിക്കും\nപരിശുദ്ധസഭയ്ക്കും ശ്ലോമോ"
    },
    {
        "type": "subtext",
        "content": "മെനഓലം…"
    },
    {
        "type": "subtext",
        "content": "നാഥാ! കൃപയാൽ മാതാവാം"
    },
    {
        "type": "subtext",
        "content": "മറിയാം നിബിശ്ലീഹാ സഹദേർ"
    },
    {
        "type": "subtext",
        "content": "ധർമ്മിഷ്ടന്മാരെന്നിവർതൻ"
    },
    {
        "type": "subtext",
        "content": "ഓർമ്മയെ വിശ്രുതമാക്കണമേ"
    },
    {
        "type": "subtext",
        "content": "/tനിൻ തിരുമെയ് ഭക്ഷിച്ചോരായ്"
    },
    {
        "type": "subtext",
        "content": "/tനിൻ ശരണേ മൃതിയാർന്നോരാം"
    },
    {
        "type": "subtext",
        "content": "വാങ്ങിപ്പോയോരെ"
    },
    {
        "type": "subtext",
        "content": "ആ നിരയിൽ ചേർത്തിടേണമേ."
    },
    {
        "type": "subtext",
        "content": "മൊറിയൊ…"
    },
    {
        "type": "link",
        "file": "marbaalaayibovooso.json"
    },
    {
        "type": "prose",
        "content": "നിൻ മാതാവു വിശുദ്ധന്മാർ…"
    },
    {
        "type": "link-collapsible",
        "file": "commonprayers/nicenecreed.json"
    }
]