[
    {
        "type": "heading",
        "content": "Danahaa perunnaallil vi. Kurbbaanaanubhavam"
    },
    {
        "type": "subheading",
        "content": "(hdau aamme hdau aamme)"
    },
    {
        "type": "subheading",
        "content": "(samrakshithajaathikalle varuvin paadin .. Enna pole)"
    },
    {
        "type": "song",
        "content": "Svaka maamo-deesaayaal-paapam pokki\nVimalatha cher-tthoneesho-raajan dhanyan.\nJaathikalle! Modippin-mariyaam chonnaall\nMal puthrasnaanatthaal-ulakam minni.\nKaikottuka-kaikottuka-yorddaane! Nee\nNinnil snaa-nam cheyvaan-mashihaa vannu.\nYorddaane-paavanamaa-kkeedum suthane\nKandappoll-bhoothangall-pedichodi.\nKara keriya mashihaaye-kaikkondeedaan\nDhavallaambara-dhaarikallaay-vanneerenmaar.\nMashihaathan snaanatthe maanicheedaan\nShubhraamshuka-bhooshitharaay-vanneerenmaar.\nYoohaanon-manavaattiyo-devam chonnaan:\nThval priyana-llayyo nyaan bhrthyan maathram.\nMaanippaan-vaanatthil-thaathan chonnaan\nIvanen priya-thanayan nyaan-ivanil preethan\nManmayanaa-lagnimayan snaanappettu.\nVaanidavum -paaridavum-kampam poondu.\nPaavanamaam-snaanatthaal-kshemam poonda\nAmbaravum -bhoothalavum -sthothram paadum\nJalajanmaa-re parishu-ddhaathmaavinte\nKunyaaduka-lle mauli u-yartthi paadin"
    }
]