[
    {
        "type": "title",
        "content": "sext"
    },
    {
        "type": "title",
        "content": "ചൊവാ മദ്ധ്യാഹ്നം"
    },
    {
        "type": "link-collapsible",
        "file": "commonprayers/kauma.json"
    },
    {
        "type": "heading",
        "content": "കോലൊ"
    },
    {
        "type": "subheading",
        "content": "(ശ്ലോമെദാബോ)"
    },
    {
        "type": "song",
        "content": "കടുമിന്നൽപ്പിണരിന്നൊപ്പം\nകണ്ടാൾ മാലാഖയെ മറിയാം\n/tചൊന്നാൻ മൃദുവായ് മറിയാമേ!\n/tശ്ലോം നാഥൻ നിന്നോടുകൂടെ\nഅത്യുന്നതനമരും നിന്നിൽ\nവാഴും നിന്നിൽ റുഹ്ക്കുദിശാ."
    },
    {
        "type": "subtext",
        "content": "ബാറെക്മോർ.... ശുബഹൊ....."
    },
    {
        "type": "song",
        "content": "ദുഷ്ടപ്പടയിന്നും കാക്കും\nകോട്ടകളാകട്ടെ നിങ്ങൾ\n/tനിബിശ്ലീഹാ! സഹദേന്മാരേ!\n/tഅസ്ഥികളെ ബഹുമാനിച്ചോർ\nപ്രാർത്ഥന മൂലമനുഗ്രഹമേ-\nറ്റവകാശിക്കണമേ രാജ്യം"
    },
    {
        "type": "subtext",
        "content": "മെനഓലം…"
    },
    {
        "type": "song",
        "content": "വിഗതർക്കോർമ്മ ഭവിക്കട്ടെ\nശരണം ജീവിത ജനതയ്ക്കും\n/tകനിവേറും താതൻ ദൈവം\n/tസംസ്തുത്യൻ ബഹുമാനാർഹൻ\nകർത്താവാം നമ്മുടെയുടയോൻ\nശരണം രണ്ടുലകങ്ങൾക്കും."
    },
    {
        "type": "subtext",
        "content": "മൊറിയൊ…"
    },
    {
        "type": "heading",
        "content": "ബോവൂസോ"
    },
    {
        "type": "link",
        "file": "lcommonprayers/marbaalaayibovooso.json"
    },
    {
        "type": "prose",
        "content": "(വി. കുർബാനയില്ലെങ്കിൽ മാർ സേവേറിയോസിന്റെ മാനീസ (പേജ് 80) വിശ്വാസപ്രമാണം, കുക്കിലിയോനുകൾ മുതലായവ ചൊല്ലി അവസാനിപ്പിക്കണം.)"
    }
]