[
    {
        "type": "heading",
        "content": "63-aam masumoor"
    },
    {
        "type": "prose",
        "content": "/ten്re dyvame! Nee en്re dyvamaakunnu; njaan ninakkaayi kaatthirikkum."
    },
    {
        "type": "prose",
        "content": "/tdaahicchu varandu vellatthinaayi aagrahikkunna bhoomiyepole, ente aathmaavu ninnekkuricchu daahicchirikkunnu. En്re jadavum ninakkaayi kaatthirikkunnu."
    },
    {
        "type": "prose",
        "content": "/tninte balavum nin്re bahumaanavum kaanmaan iprakaaram sathyamaayittu njaan ninne nokki."
    },
    {
        "type": "prose",
        "content": "/tenthennaal nin്re karuna jeevanekkaal nallathaakunnu; ente adharangal ninne sthuthikkum."
    },
    {
        "type": "prose",
        "content": "/tnjaan jeevanotirikkumpol iprakaaram njaan ninne vaazhtthukayum, nin്re naamatthil ente kykal uyartthukayum cheyyum."
    },
    {
        "type": "prose",
        "content": "/tente aathmaavu kozhuppum medasumkondennapole pushtiyaakum; en്re vaayu sthuthiyulla adharangalkondu ninne mahatthuvappetutthukayum cheyyum."
    },
    {
        "type": "prose",
        "content": "/ten്re kitakkamel njaan ninne ortthu; raathri kaalangalil njaan ninne dhyaanikkukayum cheythu."
    },
    {
        "type": "prose",
        "content": "/tenthennaal nee enikku sahaayakkaaranaayittheernnu. Nin്re chirakukalute nizhalil njaan maraykkappetum."
    },
    {
        "type": "prose",
        "content": "/tente aathmaavu ninne pinthutarnnu; nin്re valathuky enne thaangukayum cheythu."
    },
    {
        "type": "prose",
        "content": "/ten്re aathmaavine nashippippaan anveshikkunnavar bhoomiyute aazhangalilekku praveshikkum."
    },
    {
        "type": "prose",
        "content": "/tavar vaalinu elpikkappetukayum, kurunarikalkku bhakshanamaayittheerukayum cheyyum; raajaavu dyvatthil santhoshikkum."
    },
    {
        "type": "prose",
        "content": "/tavanekkondu aanayitunna evanum pukazhchayundaakum; enthennaal asathyam parayunnavarute vaayu ataykkappetum."
    },
    {
        "type": "prose",
        "content": "/tdyvame! Sthuthi ninakku yogyamaakunnu."
    },
    {
        "type": "subtext",
        "content": "baarekmor. Shubaho ... Menaolam …."
    }
]