[
    {
        "type": "title",
        "content": "māṟ aprēṁ-māṟ tēvōdōṟōs"
    },
    {
        "type": "subheading",
        "content": "(valiya nōmpil 1-āṁ śaniyāz‌ca)"
    },
    {
        "type": "subheading",
        "content": "(eṭṭāṁ rāgaṁ)"
    },
    {
        "type": "link",
        "file": "qurbanaSongs/feastStEphrem/eveningGospel.json"
    },
    {
        "type": "link",
        "file": "qurbanaSongs/feastStEphrem/morningGospel.json"
    },
    {
        "type": "link",
        "file": "qurbanaSongs/feastStEphrem/qurbanaGospel.json"
    },
    {
        "type": "link",
        "file": "qurbanaSongs/feastStEphrem/kasolikki.json"
    },
    {
        "type": "link",
        "file": "qurbanaSongs/feastStEphrem/hoothomo.json"
    }
]