[
    {
        "type": "heading",
        "content": "ēvaṉgēlikku śēṣaṁ"
    },
    {
        "type": "subheading",
        "content": "(tātaṉ ślōmmō ... enna pōle)"
    },
    {
        "type": "song",
        "content": "taṉ kalppanayāl bhr̥tyanmāṟ-kalppātraṅṅaḷilēŧŧiya nīṟ\nsvāduṁ mēnmayumēṟīṭuṁ-vīññākki tīṟttāṉ kaṟttaṉ\nmaṇavāḷanu tuṇa ceytōne pānaṁ ceytōṟ kīṟtticcu.\nvīññ virunnil tīṟnnatināl-varane āgatarellāruṁ\nnindikkunnatu kaṇṭāṟē-kaṟttāvēŧŧaṁ duḥkhiccu\nsnēhaṁ mūlaṁ kal‌piccu-veḷḷatte nal vīññākki."
    }
]